[
  {
    "ContainingType": "CybergymHRS.API.Controllers.AccountController",
    "Method": "Login",
    "RelativePath": "api/Account/login",
    "HttpMethod": "POST",
    "IsController": true,
    "Order": 0,
    "Parameters": [
      {
        "Name": "model",
        "Type": "CybergymHRS.Core.DTOs.LoginDto",
        "IsRequired": true
      }
    ],
    "ReturnTypes": []
  },
  {
    "ContainingType": "CybergymHRS.API.Controllers.AccountController",
    "Method": "Logout",
    "RelativePath": "api/Account/logout",
    "HttpMethod": "POST",
    "IsController": true,
    "Order": 0,
    "Parameters": [],
    "ReturnTypes": []
  },
  {
    "ContainingType": "CybergymHRS.API.Controllers.AccountController",
    "Method": "Register",
    "RelativePath": "api/Account/register",
    "HttpMethod": "POST",
    "IsController": true,
    "Order": 0,
    "Parameters": [
      {
        "Name": "model",
        "Type": "CybergymHRS.Core.DTOs.RegisterDto",
        "IsRequired": true
      }
    ],
    "ReturnTypes": []
  },
  {
    "ContainingType": "CybergymHRS.API.Controllers.ReservationsController",
    "Method": "GetAll",
    "RelativePath": "api/Reservations",
    "HttpMethod": "GET",
    "IsController": true,
    "Order": 0,
    "Parameters": [],
    "ReturnTypes": []
  },
  {
    "ContainingType": "CybergymHRS.API.Controllers.ReservationsController",
    "Method": "Create",
    "RelativePath": "api/Reservations",
    "HttpMethod": "POST",
    "IsController": true,
    "Order": 0,
    "Parameters": [
      {
        "Name": "reservationDto",
        "Type": "CybergymHRS.Core.DTOs.CreateReservationDto",
        "IsRequired": true
      }
    ],
    "ReturnTypes": []
  },
  {
    "ContainingType": "CybergymHRS.API.Controllers.ReservationsController",
    "Method": "GetById",
    "RelativePath": "api/Reservations/{id}",
    "HttpMethod": "GET",
    "IsController": true,
    "Order": 0,
    "Parameters": [
      {
        "Name": "id",
        "Type": "System.Int32",
        "IsRequired": true
      }
    ],
    "ReturnTypes": []
  },
  {
    "ContainingType": "CybergymHRS.API.Controllers.ReservationsController",
    "Method": "Update",
    "RelativePath": "api/Reservations/{id}",
    "HttpMethod": "PUT",
    "IsController": true,
    "Order": 0,
    "Parameters": [
      {
        "Name": "id",
        "Type": "System.Int32",
        "IsRequired": true
      },
      {
        "Name": "reservationDto",
        "Type": "CybergymHRS.Core.DTOs.UpdateReservationDto",
        "IsRequired": true
      }
    ],
    "ReturnTypes": []
  },
  {
    "ContainingType": "CybergymHRS.API.Controllers.ReservationsController",
    "Method": "Delete",
    "RelativePath": "api/Reservations/{id}",
    "HttpMethod": "DELETE",
    "IsController": true,
    "Order": 0,
    "Parameters": [
      {
        "Name": "id",
        "Type": "System.Int32",
        "IsRequired": true
      }
    ],
    "ReturnTypes": []
  },
  {
    "ContainingType": "CybergymHRS.API.Controllers.RoomsController",
    "Method": "GetAll",
    "RelativePath": "api/Rooms",
    "HttpMethod": "GET",
    "IsController": true,
    "Order": 0,
    "Parameters": [],
    "ReturnTypes": []
  },
  {
    "ContainingType": "CybergymHRS.API.Controllers.RoomsController",
    "Method": "Create",
    "RelativePath": "api/Rooms",
    "HttpMethod": "POST",
    "IsController": true,
    "Order": 0,
    "Parameters": [
      {
        "Name": "roomDto",
        "Type": "CreateRoomDto",
        "IsRequired": true
      }
    ],
    "ReturnTypes": []
  },
  {
    "ContainingType": "CybergymHRS.API.Controllers.RoomsController",
    "Method": "GetById",
    "RelativePath": "api/Rooms/{id}",
    "HttpMethod": "GET",
    "IsController": true,
    "Order": 0,
    "Parameters": [
      {
        "Name": "id",
        "Type": "System.Int32",
        "IsRequired": true
      }
    ],
    "ReturnTypes": []
  },
  {
    "ContainingType": "CybergymHRS.API.Controllers.RoomsController",
    "Method": "Update",
    "RelativePath": "api/Rooms/{id}",
    "HttpMethod": "PUT",
    "IsController": true,
    "Order": 0,
    "Parameters": [
      {
        "Name": "id",
        "Type": "System.Int32",
        "IsRequired": true
      },
      {
        "Name": "room",
        "Type": "CybergymHRS.Core.Models.Room",
        "IsRequired": true
      }
    ],
    "ReturnTypes": []
  },
  {
    "ContainingType": "CybergymHRS.API.Controllers.RoomsController",
    "Method": "Delete",
    "RelativePath": "api/Rooms/{id}",
    "HttpMethod": "DELETE",
    "IsController": true,
    "Order": 0,
    "Parameters": [
      {
        "Name": "id",
        "Type": "System.Int32",
        "IsRequired": true
      }
    ],
    "ReturnTypes": []
  }
]